mantaray-0.1.2.dist-info/METADATA
mantaray-0.1.2.dist-info/WHEEL
mantaray-0.1.2.dist-info/licenses/LICENSE-APACHE
mantaray-0.1.2.dist-info/licenses/LICENSE-MIT
mantaray/__init__.py
mantaray/_mantaray.cpython-310-darwin.so
mantaray/core.py
mantaray/datasets.py
mantaray/support.py
mantaray-0.1.2.dist-info/RECORD
