Metadata-Version: 2.4
Name: mantaray
Version: 0.1.2
Classifier: Programming Language :: Rust
Classifier: Programming Language :: Python :: Implementation :: CPython
Classifier: Programming Language :: Python :: Implementation :: PyPy
Requires-Dist: cffi>=1.14.0
Requires-Dist: xarray>=2023
Requires-Dist: pooch>=1.8.2
Requires-Dist: tqdm>=4.67.1
Requires-Dist: netcdf4>=1.5.7 ; extra == 'netcdf'
Requires-Dist: uv>=0.8 ; extra == 'dev'
Requires-Dist: pytest>=7.0 ; extra == 'test'
Requires-Dist: pytest-cov>=3.0 ; extra == 'test'
Requires-Dist: pytest-xdist>=3.0 ; extra == 'test'
Requires-Dist: netcdf4>=1.5.7 ; extra == 'test'
Provides-Extra: netcdf
Provides-Extra: dev
Provides-Extra: test
License-File: LICENSE-APACHE
License-File: LICENSE-MIT
Summary: Tracing rays
Home-Page: https://github.com/mines-oceanography/mantaray
Author-email: Bryce Irving <bryceirving@mines.edu>, Guilherme Castelao <guilherme@castelao.net>, Nicholas Pizzo <nicholas.pizzo@uri.edu>, Bia Villas Boas <villasboas@mines.edu>
License-Expression: MIT OR Apache-2.0
Requires-Python: >=3.10
